certbot_dns_aliyun/__init__.py
certbot_dns_aliyun/dns_aliyun.py
certbot_dns_alidomain-0.1.0.dev1.dist-info/LICENSE.txt
certbot_dns_alidomain-0.1.0.dev1.dist-info/METADATA
certbot_dns_alidomain-0.1.0.dev1.dist-info/WHEEL
certbot_dns_alidomain-0.1.0.dev1.dist-info/entry_points.txt
certbot_dns_alidomain-0.1.0.dev1.dist-info/top_level.txt
certbot_dns_alidomain-0.1.0.dev1.dist-info/RECORD
